fa_htmlstream-1.2.1.dist-info/licenses/LICENSE.txt
htmlstream/__init__.py
htmlstream/cursor.py
htmlstream/parse.py
htmlstream/py.typed
fa_htmlstream-1.2.1.dist-info/METADATA
fa_htmlstream-1.2.1.dist-info/WHEEL
fa_htmlstream-1.2.1.dist-info/top_level.txt
fa_htmlstream-1.2.1.dist-info/RECORD
