Metadata-Version: 2.4
Name: fa-htmlstream
Version: 1.2.1
Summary: A simple streaming HTML parser
Author-email: Ray Wallace <rwallace3@proton.me>
License-Expression: LGPL-3.0-or-later
Project-URL: Home, https://halfpanda.dev/
Project-URL: Repository, https://github.com/faboo/htmlstream.git
Classifier: Programming Language :: Python :: 3
Classifier: Operating System :: OS Independent
Classifier: Intended Audience :: Developers
Classifier: Topic :: Software Development :: Compilers
Classifier: Topic :: Text Processing
Classifier: Topic :: Text Processing :: Markup :: HTML
Classifier: Typing :: Typed
Requires-Python: >=3.10
License-File: LICENSE.txt
Provides-Extra: dev
Requires-Dist: tox; extra == "dev"
Requires-Dist: mypy; extra == "dev"
Requires-Dist: pylint; extra == "dev"
Dynamic: license-file
